netk/xwt/__init__.py
netk/xwt/application.py
netk/xwt/libs/__init__.py
netk/xwt/libs/Xwt.dll
netk/xwt/libs/Xwt.WPF.dll
netk/xwt/run.py
netk/xwt/window.py
netk_xwt-0.1.0.dist-info/METADATA
netk_xwt-0.1.0.dist-info/WHEEL
netk_xwt-0.1.0.dist-info/RECORD
