Metadata-Version: 2.1
Name: netk-xwt
Version: 0.1.0
Summary: 
Author: XiangQinxi
Author-email: XiangQinxi@outlook.com
Requires-Python: >=3.7,<4.0
Classifier: Programming Language :: Python :: 3
Classifier: Programming Language :: Python :: 3.7
Classifier: Programming Language :: Python :: 3.8
Classifier: Programming Language :: Python :: 3.9
Classifier: Programming Language :: Python :: 3.10
Classifier: Programming Language :: Python :: 3.11
Classifier: Programming Language :: Python :: 3.12
Requires-Dist: netk (>=0.1,<0.2)
